Workbook

Sheet 05
R1: Filter | S1: Filter | T1: Filter | U1: Filter | V1: Filter | W1: Filter | X1: Filter | Y1: Filter | Z1: Filter | AA1: Filter | AB1: Filter | AC1: Filter | AD1: Filter | AE1: Filter | AF1: Filter | AG1: Filter | AH1: Filter | AI1: Filter | AJ1: Filter | AK1: Filter | AL1: Filter | AM1: Filter | AN1: Filter | AO1: Filter | AP1: Filter | AQ1: Filter | AR1: Filter | AS1: Filter | AT1: Filter | AU1: Filter | AV1: Filter | AW1: Filter | AX1: Filter | AY1: Filter | AZ1: Filter | BA1: Filter | BB1: Filter | BC1: Filter | BD1: Filter | BE1: Filter | BF1: Filter | BG1: Filter | BH1: Filter | BI1: Filter | BJ1: Filter | BK1: Filter | BL1: Filter
R2: =IFERROR(__xludf.DUMMYFUNCTION(" QUERY('DATA REAL'!$A$2:$B1000,""SELECT B WHERE A = '""&$B16&""'"")"),"#REF!") -> #REF! | S2: =IFERROR(__xludf.DUMMYFUNCTION(" QUERY('DATA REAL'!$A$2:$B1000,""SELECT B WHERE A = '""&$B17&""'"")"),"#REF!") -> #REF! | T2: =IFERROR(__xludf.DUMMYFUNCTION(" QUERY('DATA REAL'!$A$2:$B1000,""SELECT B WHERE A = '""&$B18&""'"")"),"#REF!") -> #REF! | U2: =IFERROR(__xludf.DUMMYFUNCTION(" QUERY('DATA REAL'!$A$2:$B1000,""SELECT B WHERE A = '""&$B19&""'"")"),"#REF!") -> #REF! | V2: =IFERROR(__xludf.DUMMYFUNCTION(" QUERY('DATA REAL'!$A$2:$B1000,""SELECT B WHERE A = '""&$B20&""'"")"),"#REF!") -> #REF! | W2: =IFERROR(__xludf.DUMMYFUNCTION(" QUERY('DATA REAL'!$A$2:$B1000,""SELECT B WHERE A = '""&$B21&""'"")"),"#REF!") -> #REF! | X2: =IFERROR(__xludf.DUMMYFUNCTION(" QUERY('DATA REAL'!$A$2:$B1000,""SELECT B WHERE A = '""&$B22&""'"")"),"#REF!") -> #REF! | Y2: =IFERROR(__xludf.DUMMYFUNCTION(" QUERY('DATA REAL'!$A$2:$B1000,""SELECT B WHERE A = '""&$B23&""'"")"),"#REF!") -> #REF! | Z2: =IFERROR(__xludf.DUMMYFUNCTION(" QUERY('DATA REAL'!$A$2:$B1000,""SELECT B WHERE A = '""&$B24&""'"")"),"#REF!") -> #REF! | AA2: =IFERROR(__xludf.DUMMYFUNCTION(" QUERY('DATA REAL'!$A$2:$B1000,""SELECT B WHERE A = '""&$B25&""'"")"),"#REF!") -> #REF! | AB2: =IFERROR(__xludf.DUMMYFUNCTION(" QUERY('DATA REAL'!$A$2:$B1000,""SELECT B WHERE A = '""&$B26&""'"")"),"#REF!") -> #REF! | AC2: =IFERROR(__xludf.DUMMYFUNCTION(" QUERY('DATA REAL'!$A$2:$B1000,""SELECT B WHERE A = '""&$B27&""'"")"),"#REF!") -> #REF! | AD2: =IFERROR(__xludf.DUMMYFUNCTION(" QUERY('DATA REAL'!$A$2:$B1000,""SELECT B WHERE A = '""&$B28&""'"")"),"#REF!") -> #REF! | AE2: =IFERROR(__xludf.DUMMYFUNCTION(" QUERY('DATA REAL'!$A$2:$B1000,""SELECT B WHERE A = '""&$B29&""'"")"),"#REF!") -> #REF! | AF2: =IFERROR(__xludf.DUMMYFUNCTION(" QUERY('DATA REAL'!$A$2:$B1000,""SELECT B WHERE A = '""&$B30&""'"")"),"#REF!") -> #REF! | AG2: =IFERROR(__xludf.DUMMYFUNCTION(" QUERY('DATA REAL'!$A$2:$B1000,""SELECT B WHERE A = '""&$B31&""'"")"),"#REF!") -> #REF! | AH2: =IFERROR(__xludf.DUMMYFUNCTION(" QUERY('DATA REAL'!$A$2:$B1000,""SELECT B WHERE A = '""&$B32&""'"")"),"#REF!") -> #REF! | AI2: =IFERROR(__xludf.DUMMYFUNCTION(" QUERY('DATA REAL'!$A$2:$B1000,""SELECT B WHERE A = '""&$B33&""'"")"),"#REF!") -> #REF! | AJ2: =IFERROR(__xludf.DUMMYFUNCTION(" QUERY('DATA REAL'!$A$2:$B1000,""SELECT B WHERE A = '""&$B34&""'"")"),"#REF!") -> #REF! | AK2: =IFERROR(__xludf.DUMMYFUNCTION(" QUERY('DATA REAL'!$A$2:$B1000,""SELECT B WHERE A = '""&$B35&""'"")"),"#REF!") -> #REF! | AL2: =IFERROR(__xludf.DUMMYFUNCTION(" QUERY('DATA REAL'!$A$2:$B1000,""SELECT B WHERE A = '""&$B36&""'"")"),"#REF!") -> #REF! | AM2: =IFERROR(__xludf.DUMMYFUNCTION(" QUERY('DATA REAL'!$A$2:$B1000,""SELECT B WHERE A = '""&$B37&""'"")"),"#REF!") -> #REF! | AN2: =IFERROR(__xludf.DUMMYFUNCTION(" QUERY('DATA REAL'!$A$2:$B1000,""SELECT B WHERE A = '""&$B38&""'"")"),"#REF!") -> #REF! | AO2: =IFERROR(__xludf.DUMMYFUNCTION(" QUERY('DATA REAL'!$A$2:$B1000,""SELECT B WHERE A = '""&$B39&""'"")"),"#REF!") -> #REF! | AP2: =IFERROR(__xludf.DUMMYFUNCTION(" QUERY('DATA REAL'!$A$2:$B1000,""SELECT B WHERE A = '""&$B40&""'"")"),"#REF!") -> #REF! | AQ2: =IFERROR(__xludf.DUMMYFUNCTION(" QUERY('DATA REAL'!$A$2:$B1000,""SELECT B WHERE A = '""&$B41&""'"")"),"#REF!") -> #REF! | AR2: =IFERROR(__xludf.DUMMYFUNCTION(" QUERY('DATA REAL'!$A$2:$B1000,""SELECT B WHERE A = '""&$B42&""'"")"),"#REF!") -> #REF! | AS2: =IFERROR(__xludf.DUMMYFUNCTION(" QUERY('DATA REAL'!$A$2:$B1000,""SELECT B WHERE A = '""&$B43&""'"")"),"#REF!") -> #REF! | AT2: =IFERROR(__xludf.DUMMYFUNCTION(" QUERY('DATA REAL'!$A$2:$B1000,""SELECT B WHERE A = '""&$B44&""'"")"),"#REF!") -> #REF! | AU2: =IFERROR(__xludf.DUMMYFUNCTION(" QUERY('DATA REAL'!$A$2:$B1000,""SELECT B WHERE A = '""&$B45&""'"")"),"#REF!") -> #REF! | AV2: =IFERROR(__xludf.DUMMYFUNCTION(" QUERY('DATA REAL'!$A$2:$B1000,""SELECT B WHERE A = '""&$B46&""'"")"),"#REF!") -> #REF! | AW2: =IFERROR(__xludf.DUMMYFUNCTION(" QUERY('DATA REAL'!$A$2:$B1000,""SELECT B WHERE A = '""&$B47&""'"")"),"#REF!") -> #REF! | AX2: =IFERROR(__xludf.DUMMYFUNCTION(" QUERY('DATA REAL'!$A$2:$B1000,""SELECT B WHERE A = '""&$B48&""'"")"),"#REF!") -> #REF! | AY2: =IFERROR(__xludf.DUMMYFUNCTION(" QUERY('DATA REAL'!$A$2:$B1000,""SELECT B WHERE A = '""&$B49&""'"")"),"#REF!") -> #REF! | AZ2: =IFERROR(__xludf.DUMMYFUNCTION(" QUERY('DATA REAL'!$A$2:$B1000,""SELECT B WHERE A = '""&$B50&""'"")"),"#REF!") -> #REF! | BA2: =IFERROR(__xludf.DUMMYFUNCTION(" QUERY('DATA REAL'!$A$2:$B1000,""SELECT B WHERE A = '""&$B51&""'"")"),"#REF!") -> #REF! | BB2: =IFERROR(__xludf.DUMMYFUNCTION(" QUERY('DATA REAL'!$A$2:$B1000,""SELECT B WHERE A = '""&$B52&""'"")"),"#REF!") -> #REF! | BC2: =IFERROR(__xludf.DUMMYFUNCTION(" QUERY('DATA REAL'!$A$2:$B1000,""SELECT B WHERE A = '""&$B53&""'"")"),"#REF!") -> #REF! | BD2: =IFERROR(__xludf.DUMMYFUNCTION(" QUERY('DATA REAL'!$A$2:$B1000,""SELECT B WHERE A = '""&$B54&""'"")"),"#REF!") -> #REF! | BE2: =IFERROR(__xludf.DUMMYFUNCTION(" QUERY('DATA REAL'!$A$2:$B1000,""SELECT B WHERE A = '""&$B55&""'"")"),"#REF!") -> #REF! | BF2: =IFERROR(__xludf.DUMMYFUNCTION(" QUERY('DATA REAL'!$A$2:$B1000,""SELECT B WHERE A = '""&$B56&""'"")"),"#REF!") -> #REF! | BG2: =IFERROR(__xludf.DUMMYFUNCTION(" QUERY('DATA REAL'!$A$2:$B1000,""SELECT B WHERE A = '""&$B57&""'"")"),"#REF!") -> #REF! | BH2: =IFERROR(__xludf.DUMMYFUNCTION(" QUERY('DATA REAL'!$A$2:$B1000,""SELECT B WHERE A = '""&$B58&""'"")"),"#REF!") -> #REF! | BI2: =IFERROR(__xludf.DUMMYFUNCTION(" QUERY('DATA REAL'!$A$2:$B1000,""SELECT B WHERE A = '""&$B59&""'"")"),"#REF!") -> #REF! | BJ2: =IFERROR(__xludf.DUMMYFUNCTION(" QUERY('DATA REAL'!$A$2:$B1000,""SELECT B WHERE A = '""&$B60&""'"")"),"#REF!") -> #REF! | BK2: =IFERROR(__xludf.DUMMYFUNCTION(" QUERY('DATA REAL'!$A$2:$B1000,""SELECT B WHERE A = '""&$B61&""'"")"),"#REF!") -> #REF! | BL2: =IFERROR(__xludf.DUMMYFUNCTION(" QUERY('DATA REAL'!$A$2:$B1000,""SELECT B WHERE A = '""&$B62&""'"")"),"#REF!") -> #REF!
D3: 234 Moo 7, Suan Phueng
D4: Ratchabuti 70180
D5: Tel : +66 81 000 7070
D6: Fax : +66 32 206 370 | G6: Invoice No
D7: www.sceneryvintagefarm.com | G7: Date
B9: Reference No. | F9: Guest Name / No.of Guest
D10: =H6
B11: Check-in Date | D11: Check-out Date | F11: No.Of Night | G11: Remark
B14: Category | C14: QTY | D14: Description | E14: Rate (per total QTY) | F14: Deposit | G14: Discount | H14: Total THB
B15: Accommodation & Inclusive Package
H16: =(E16*C16)-F16-G16 -> 0 | N16: ='05'!$E16*'05'!$C16 -> 0
E17: =IFERROR(VLOOKUP('05'!$D17,'DATA REAL'!B:F,2,FALSE),"") | H17: =('05'!$E17*'05'!$C17)-'05'!$F17-'05'!$G17 -> 0 | N17: ='05'!$E17*'05'!$C17 -> 0
E18: =IFERROR(VLOOKUP('05'!$D18,'DATA REAL'!B:F,2,FALSE),"") | H18: =('05'!$E18*'05'!$C18)-'05'!$F18-'05'!$G18 -> 0 | N18: ='05'!$E18*'05'!$C18 -> 0
E19: =IFERROR(VLOOKUP('05'!$D19,'DATA REAL'!B:F,2,FALSE),"") | H19: =('05'!$E19*'05'!$C19)-'05'!$F19-'05'!$G19 -> 0 | N19: ='05'!$E19*'05'!$C19 -> 0
E20: =IFERROR(VLOOKUP('05'!$D20,'DATA REAL'!B:F,2,FALSE),"") | H20: =('05'!$E20*'05'!$C20)-'05'!$F20-'05'!$G20 -> 0 | N20: ='05'!$E20*'05'!$C20 -> 0
E21: =IFERROR(VLOOKUP('05'!$D21,'DATA REAL'!B:F,2,FALSE),"") | H21: =('05'!$E21*'05'!$C21)-'05'!$F21-'05'!$G21 -> 0 | N21: ='05'!$E21*'05'!$C21 -> 0
E22: =IFERROR(VLOOKUP('05'!$D22,'DATA REAL'!B:F,2,FALSE),"") | H22: =('05'!$E22*'05'!$C22)-'05'!$F22-'05'!$G22 -> 0 | N22: ='05'!$E22*'05'!$C22 -> 0
E23: =IFERROR(VLOOKUP('05'!$D23,'DATA REAL'!B:F,2,FALSE),"") | H23: =('05'!$E23*'05'!$C23)-'05'!$F23-'05'!$G23 -> 0 | N23: ='05'!$E23*'05'!$C23 -> 0
E24: =IFERROR(VLOOKUP('05'!$D24,'DATA REAL'!B:F,2,FALSE),"") | H24: =('05'!$E24*'05'!$C24)-'05'!$F24-'05'!$G24 -> 0 | N24: ='05'!$E24*'05'!$C24 -> 0
E25: =IFERROR(VLOOKUP('05'!$D25,'DATA REAL'!B:F,2,FALSE),"") | H25: =('05'!$E25*'05'!$C25)-'05'!$F25-'05'!$G25 -> 0 | N25: ='05'!$E25*'05'!$C25 -> 0
E26: =IFERROR(VLOOKUP('05'!$D26,'DATA REAL'!B:F,2,FALSE),"") | H26: =('05'!$E26*'05'!$C26)-'05'!$F26-'05'!$G26 -> 0 | J26: ราคาแต่ละรายการ | K26: ราคาหลังหักส่วนลด 10% | L26: ส่วนต่าง | N26: ='05'!$E26*'05'!$C26 -> 0
B27: Food and Beverages (add-on) and Other Expenses | N27: ='05'!$E27*'05'!$C27 -> 0
E28: =IFERROR(VLOOKUP('05'!$D28,'DATA REAL'!B:F,2,FALSE),"") | G28: =IFERROR(VLOOKUP('05'!$D28,'DATA REAL'!A:F,6,FALSE),"")*'05'!$C28 -> 0 | H28: =('05'!$E28*'05'!$C28)-'05'!$F28-'05'!$G28 -> 0 | J28: =IFERROR(VLOOKUP('05'!$D28,DATA!C:D,2,FALSE),"") | K28: =IFERROR(VLOOKUP('05'!$D28,DATA!C:F,4,FALSE),"") | L28: =J28-K28 -> 0 | N28: ='05'!$E28*'05'!$C28 -> 0
E29: =IFERROR(VLOOKUP('05'!$D29,'DATA REAL'!B:F,2,FALSE),"") | G29: =IFERROR(VLOOKUP('05'!$D29,DATA!C:G,5,FALSE),"")*'05'!$C29 -> 0 | H29: =('05'!$E29*'05'!$C29)-'05'!$F29-'05'!$G29 -> 0 | J29: =IFERROR(VLOOKUP('05'!$D29,DATA!C:D,2,FALSE),"") | K29: =IFERROR(VLOOKUP('05'!$D29,DATA!C:F,4,FALSE),"") | L29: =J29-K29 -> 0 | N29: ='05'!$E29*'05'!$C29 -> 0
E30: =IFERROR(VLOOKUP('05'!$D30,'DATA REAL'!B:F,2,FALSE),"") | G30: =IFERROR(VLOOKUP('05'!$D30,DATA!C:G,5,FALSE),"")*'05'!$C30 -> 0 | H30: =('05'!$E30*'05'!$C30)-'05'!$F30-'05'!$G30 -> 0 | N30: ='05'!$E30*'05'!$C30 -> 0
E31: =IFERROR(VLOOKUP('05'!$D31,'DATA REAL'!B:F,2,FALSE),"") | G31: =IFERROR(VLOOKUP('05'!$D31,DATA!C:G,5,FALSE),"")*'05'!$C31 -> 0 | H31: =('05'!$E31*'05'!$C31)-'05'!$F31-'05'!$G31 -> 0 | N31: ='05'!$E31*'05'!$C31 -> 0
E32: =IFERROR(VLOOKUP('05'!$D32,'DATA REAL'!B:F,2,FALSE),"") | G32: =IFERROR(VLOOKUP('05'!$D32,DATA!C:G,5,FALSE),"")*'05'!$C32 -> 0 | H32: =('05'!$E32*'05'!$C32)-'05'!$F32-'05'!$G32 -> 0 | N32: ='05'!$E32*'05'!$C32 -> 0
E33: =IFERROR(VLOOKUP('05'!$D33,'DATA REAL'!B:F,2,FALSE),"") | G33: =IFERROR(VLOOKUP('05'!$D33,DATA!C:G,5,FALSE),"")*'05'!$C33 -> 0 | H33: =('05'!$E33*'05'!$C33)-'05'!$F33-'05'!$G33 -> 0 | N33: ='05'!$E33*'05'!$C33 -> 0
E34: =IFERROR(VLOOKUP('05'!$D34,'DATA REAL'!B:F,2,FALSE),"") | G34: =IFERROR(VLOOKUP('05'!$D34,DATA!C:G,5,FALSE),"")*'05'!$C34 -> 0 | H34: =('05'!$E34*'05'!$C34)-'05'!$F34-'05'!$G34 -> 0 | J34: =IFERROR(VLOOKUP('05'!$D34,DATA!C:D,2,FALSE),"") | K34: =IFERROR(VLOOKUP('05'!$D34,DATA!C:F,4,FALSE),"") | L34: =J34-K34 -> 0 | N34: ='05'!$E34*'05'!$C34 -> 0
E35: =IFERROR(VLOOKUP('05'!$D35,'DATA REAL'!B:F,2,FALSE),"") | G35: =IFERROR(VLOOKUP('05'!$D35,DATA!C:G,5,FALSE),"")*'05'!$C35 -> 0 | H35: =('05'!$E35*'05'!$C35)-'05'!$F35-'05'!$G35 -> 0 | J35: =IFERROR(VLOOKUP('05'!$D35,DATA!C:D,2,FALSE),"") | K35: =IFERROR(VLOOKUP('05'!$D35,DATA!C:F,4,FALSE),"") | L35: =J35-K35 -> 0 | N35: ='05'!$E35*'05'!$C35 -> 0
E36: =IFERROR(VLOOKUP('05'!$D36,'DATA REAL'!B:F,2,FALSE),"") | G36: =IFERROR(VLOOKUP('05'!$D36,DATA!C:G,5,FALSE),"")*'05'!$C36 -> 0 | H36: =('05'!$E36*'05'!$C36)-'05'!$F36-'05'!$G36 -> 0 | J36: =IFERROR(VLOOKUP('05'!$D36,DATA!C:D,2,FALSE),"") | K36: =IFERROR(VLOOKUP('05'!$D36,DATA!C:F,4,FALSE),"") | L36: =J36-K36 -> 0 | N36: ='05'!$E36*'05'!$C36 -> 0
E37: =IFERROR(VLOOKUP('05'!$D37,'DATA REAL'!B:F,2,FALSE),"") | G37: =IFERROR(VLOOKUP('05'!$D37,DATA!C:G,5,FALSE),"")*'05'!$C37 -> 0 | H37: =('05'!$E37*'05'!$C37)-'05'!$F37-'05'!$G37 -> 0 | J37: =IFERROR(VLOOKUP('05'!$D37,DATA!C:D,2,FALSE),"") | K37: =IFERROR(VLOOKUP('05'!$D37,DATA!C:F,4,FALSE),"") | L37: =J37-K37 -> 0 | N37: ='05'!$E37*'05'!$C37 -> 0
E38: =IFERROR(VLOOKUP('05'!$D38,'DATA REAL'!B:F,2,FALSE),"") | G38: =IFERROR(VLOOKUP('05'!$D38,DATA!C:G,5,FALSE),"")*'05'!$C38 -> 0 | H38: =('05'!$E38*'05'!$C38)-'05'!$F38-'05'!$G38 -> 0 | J38: =IFERROR(VLOOKUP('05'!$D38,DATA!C:D,2,FALSE),"") | K38: =IFERROR(VLOOKUP('05'!$D38,DATA!C:F,4,FALSE),"") | L38: =J38-K38 -> 0 | N38: ='05'!$E38*'05'!$C38 -> 0
E39: =IFERROR(VLOOKUP('05'!$D39,'DATA REAL'!B:F,2,FALSE),"") | G39: =IFERROR(VLOOKUP('05'!$D39,DATA!C:G,5,FALSE),"")*'05'!$C39 -> 0 | H39: =('05'!$E39*'05'!$C39)-'05'!$F39-'05'!$G39 -> 0 | N39: ='05'!$E39*'05'!$C39 -> 0
E40: =IFERROR(VLOOKUP('05'!$D40,'DATA REAL'!B:F,2,FALSE),"") | G40: =IFERROR(VLOOKUP('05'!$D40,DATA!C:G,5,FALSE),"")*'05'!$C40 -> 0 | H40: =('05'!$E40*'05'!$C40)-'05'!$F40-'05'!$G40 -> 0 | N40: ='05'!$E40*'05'!$C40 -> 0
E41: =IFERROR(VLOOKUP('05'!$D41,'DATA REAL'!B:F,2,FALSE),"") | G41: =IFERROR(VLOOKUP('05'!$D41,DATA!C:G,5,FALSE),"")*'05'!$C41 -> 0 | H41: =('05'!$E41*'05'!$C41)-'05'!$F41-'05'!$G41 -> 0 | N41: ='05'!$E41*'05'!$C41 -> 0
E42: =IFERROR(VLOOKUP('05'!$D42,'DATA REAL'!B:F,2,FALSE),"") | G42: =IFERROR(VLOOKUP('05'!$D42,DATA!C:G,5,FALSE),"")*'05'!$C42 -> 0 | H42: =('05'!$E42*'05'!$C42)-'05'!$F42-'05'!$G42 -> 0 | N42: ='05'!$E42*'05'!$C42 -> 0
E43: =IFERROR(VLOOKUP('05'!$D43,'DATA REAL'!B:F,2,FALSE),"") | G43: =IFERROR(VLOOKUP('05'!$D43,DATA!C:G,5,FALSE),"")*'05'!$C43 -> 0 | H43: =('05'!$E43*'05'!$C43)-'05'!$F43-'05'!$G43 -> 0 | N43: ='05'!$E43*'05'!$C43 -> 0
E44: =IFERROR(VLOOKUP('05'!$D44,'DATA REAL'!B:F,2,FALSE),"") | G44: =IFERROR(VLOOKUP('05'!$D44,DATA!C:G,5,FALSE),"")*'05'!$C44 -> 0 | H44: =('05'!$E44*'05'!$C44)-'05'!$F44-'05'!$G44 -> 0 | J44: =IFERROR(VLOOKUP('05'!$D44,DATA!C:D,2,FALSE),"") | K44: =IFERROR(VLOOKUP('05'!$D44,DATA!C:F,4,FALSE),"") | L44: =J44-K44 -> 0 | N44: ='05'!$E44*'05'!$C44 -> 0
E45: =IFERROR(VLOOKUP('05'!$D45,'DATA REAL'!B:F,2,FALSE),"") | G45: =IFERROR(VLOOKUP('05'!$D45,DATA!C:G,5,FALSE),"")*'05'!$C45 -> 0 | H45: =('05'!$E45*'05'!$C45)-'05'!$F45-'05'!$G45 -> 0 | J45: =IFERROR(VLOOKUP('05'!$D45,DATA!C:D,2,FALSE),"") | K45: =IFERROR(VLOOKUP('05'!$D45,DATA!C:F,4,FALSE),"") | L45: =J45-K45 -> 0 | N45: ='05'!$E45*'05'!$C45 -> 0
E46: =IFERROR(VLOOKUP('05'!$D46,'DATA REAL'!B:F,2,FALSE),"") | G46: =IFERROR(VLOOKUP('05'!$D46,DATA!C:G,5,FALSE),"")*'05'!$C46 -> 0 | H46: =('05'!$E46*'05'!$C46)-'05'!$F46-'05'!$G46 -> 0 | J46: =IFERROR(VLOOKUP('05'!$D46,DATA!C:D,2,FALSE),"") | K46: =IFERROR(VLOOKUP('05'!$D46,DATA!C:F,4,FALSE),"") | L46: =J46-K46 -> 0 | N46: ='05'!$E46*'05'!$C46 -> 0
E47: =IFERROR(VLOOKUP('05'!$D47,'DATA REAL'!B:F,2,FALSE),"") | G47: =IFERROR(VLOOKUP('05'!$D47,DATA!C:G,5,FALSE),"")*'05'!$C47 -> 0 | H47: =('05'!$E47*'05'!$C47)-'05'!$F47-'05'!$G47 -> 0 | J47: =IFERROR(VLOOKUP('05'!$D47,DATA!C:D,2,FALSE),"") | K47: =IFERROR(VLOOKUP('05'!$D47,DATA!C:F,4,FALSE),"") | L47: =J47-K47 -> 0 | N47: ='05'!$E47*'05'!$C47 -> 0
E48: =IFERROR(VLOOKUP('05'!$D48,'DATA REAL'!B:F,2,FALSE),"") | G48: =IFERROR(VLOOKUP('05'!$D48,DATA!C:G,5,FALSE),"")*'05'!$C48 -> 0 | H48: =('05'!$E48*'05'!$C48)-'05'!$F48-'05'!$G48 -> 0 | J48: =IFERROR(VLOOKUP('05'!$D48,DATA!C:D,2,FALSE),"") | K48: =IFERROR(VLOOKUP('05'!$D48,DATA!C:F,4,FALSE),"") | L48: =J48-K48 -> 0 | N48: ='05'!$E48*'05'!$C48 -> 0
E49: =IFERROR(VLOOKUP('05'!$D49,'DATA REAL'!B:F,2,FALSE),"") | G49: =IFERROR(VLOOKUP('05'!$D49,DATA!C:G,5,FALSE),"")*'05'!$C49 -> 0 | H49: =('05'!$E49*'05'!$C49)-'05'!$F49-'05'!$G49 -> 0 | J49: =IFERROR(VLOOKUP('05'!$D49,DATA!C:D,2,FALSE),"") | K49: =IFERROR(VLOOKUP('05'!$D49,DATA!C:F,4,FALSE),"") | L49: =J49-K49 -> 0 | N49: ='05'!$E49*'05'!$C49 -> 0
E50: =IFERROR(VLOOKUP('05'!$D50,'DATA REAL'!B:F,2,FALSE),"") | G50: =IFERROR(VLOOKUP('05'!$D50,DATA!C:G,5,FALSE),"")*'05'!$C50 -> 0 | H50: =('05'!$E50*'05'!$C50)-'05'!$F50-'05'!$G50 -> 0 | J50: =IFERROR(VLOOKUP('05'!$D50,DATA!C:D,2,FALSE),"") | K50: =IFERROR(VLOOKUP('05'!$D50,DATA!C:F,4,FALSE),"") | L50: =J50-K50 -> 0 | N50: ='05'!$E50*'05'!$C50 -> 0
E51: =IFERROR(VLOOKUP('05'!$D51,'DATA REAL'!B:F,2,FALSE),"") | G51: =IFERROR(VLOOKUP('05'!$D51,DATA!C:G,5,FALSE),"")*'05'!$C51 -> 0 | H51: =('05'!$E51*'05'!$C51)-'05'!$F51-'05'!$G51 -> 0 | J51: =IFERROR(VLOOKUP('05'!$D51,DATA!C:D,2,FALSE),"") | K51: =IFERROR(VLOOKUP('05'!$D51,DATA!C:F,4,FALSE),"") | L51: =J51-K51 -> 0 | N51: ='05'!$E51*'05'!$C51 -> 0
E52: =IFERROR(VLOOKUP('05'!$D52,'DATA REAL'!B:F,2,FALSE),"") | G52: =IFERROR(VLOOKUP('05'!$D52,DATA!C:G,5,FALSE),"")*'05'!$C52 -> 0 | H52: =('05'!$E52*'05'!$C52)-'05'!$F52-'05'!$G52 -> 0 | J52: =IFERROR(VLOOKUP('05'!$D52,DATA!C:D,2,FALSE),"") | K52: =IFERROR(VLOOKUP('05'!$D52,DATA!C:F,4,FALSE),"") | L52: =J52-K52 -> 0 | N52: ='05'!$E52*'05'!$C52 -> 0
E53: =IFERROR(VLOOKUP('05'!$D53,'DATA REAL'!B:F,2,FALSE),"") | G53: =IFERROR(VLOOKUP('05'!$D53,DATA!C:G,5,FALSE),"")*'05'!$C53 -> 0 | H53: =('05'!$E53*'05'!$C53)-'05'!$F53-'05'!$G53 -> 0 | J53: =IFERROR(VLOOKUP('05'!$D53,DATA!C:D,2,FALSE),"") | K53: =IFERROR(VLOOKUP('05'!$D53,DATA!C:F,4,FALSE),"") | L53: =J53-K53 -> 0 | N53: ='05'!$E53*'05'!$C53 -> 0
E54: =IFERROR(VLOOKUP('05'!$D54,'DATA REAL'!B:F,2,FALSE),"") | G54: =IFERROR(VLOOKUP('05'!$D54,DATA!C:G,5,FALSE),"")*'05'!$C54 -> 0 | H54: =('05'!$E54*'05'!$C54)-'05'!$F54-'05'!$G54 -> 0 | J54: =IFERROR(VLOOKUP('05'!$D54,DATA!C:D,2,FALSE),"") | K54: =IFERROR(VLOOKUP('05'!$D54,DATA!C:F,4,FALSE),"") | L54: =J54-K54 -> 0 | N54: ='05'!$E54*'05'!$C54 -> 0
E55: =IFERROR(VLOOKUP('05'!$D55,'DATA REAL'!B:F,2,FALSE),"") | G55: =IFERROR(VLOOKUP('05'!$D55,DATA!C:G,5,FALSE),"")*'05'!$C55 -> 0 | H55: =('05'!$E55*'05'!$C55)-'05'!$F55-'05'!$G55 -> 0 | J55: =IFERROR(VLOOKUP('05'!$D55,DATA!C:D,2,FALSE),"") | K55: =IFERROR(VLOOKUP('05'!$D55,DATA!C:F,4,FALSE),"") | L55: =J55-K55 -> 0 | N55: ='05'!$E55*'05'!$C55 -> 0
B57: I agree that my liability for this bill is not waived and agree to be held personally liable in the event that the indicated person, company or association fails to pay for any part of the full amount of these charges. | G57: Total | H57: {=SUM($E$16:$E$26*C16:C26)+SUM($E$28:$E$55*$C$28:$C$55)} -> 0 | N57: =SUM(N16:N55) -> 0 | O57: ใช้เทียบกับยอด Total ว่าถูกหรือไม่
G58: Deposit | H58: =SUM($F$16:$F$55) -> 0
G59: Discount | H59: =SUM($G$15:$G$55) -> 0
G60: Outstanding | H60: =H57-H58-H59 -> 0
H61: THAI BAHT
D64: Guest Signature | G64: Receptionist
